pentestflow/__init__.py
pentestflow-0.0.1.dist-info/licenses/LICENSE
pentestflow-0.0.1.dist-info/METADATA
pentestflow-0.0.1.dist-info/WHEEL
pentestflow-0.0.1.dist-info/top_level.txt
pentestflow-0.0.1.dist-info/RECORD
